blackbox.py
chat.py
deepinfra.py
deepseek.py
gemini.py
gpt.py
image.py
voice.py
wormgpt.py
HalaGPT-1.25.6.dist-info/METADATA
HalaGPT-1.25.6.dist-info/WHEEL
HalaGPT-1.25.6.dist-info/top_level.txt
HalaGPT-1.25.6.dist-info/RECORD
