Metadata-Version: 2.2
Name: HalaGPT
Version: 1.25.6
Summary: Library for interacting with multiple AI APIs
Author: Dark
Classifier: Programming Language :: Python :: 3
Classifier: License :: OSI Approved :: MIT License
Classifier: Operating System :: OS Independent
Requires-Python: >=3.6
Requires-Dist: requests
Requires-Dist: user_agent
Requires-Dist: beautifulsoup4
Requires-Dist: pycountry
Requires-Dist: mnemonic
Dynamic: author
Dynamic: classifier
Dynamic: description
Dynamic: description-content-type
Dynamic: requires-dist
Dynamic: requires-python
Dynamic: summary
